[
  { "name": "DarkTV 1", "type": "stalker", "url": "http://iptv.darktv.in/c", "params": { "mac": "00:1A:79:C5:C9:F3" } },
  { "name": "DarkTV 2", "type": "stalker", "url": "http://iptv.darktv.in/c", "params": { "mac": "00:1A:79:3A:1F:07" } },
  { "name": "DarkTV 3", "type": "stalker", "url": "http://iptv.darktv.in/c", "params": { "mac": "00:1A:79:51:19:FD" } },
  { "name": "DarkTV 4", "type": "stalker", "url": "http://iptv.darktv.in/c", "params": { "mac": "00:1A:79:B3:23:62" } },
  { "name": "DarkTV 5", "type": "stalker", "url": "http://iptv.darktv.in/c", "params": { "mac": "00:1A:79:D7:7F:06" } },
  { "name": "DarkTV 6", "type": "stalker", "url": "http://iptv.darktv.in/c", "params": { "mac": "00:1A:79:C8:12:A2" } },
  { "name": "DarkTV 7", "type": "stalker", "url": "http://iptv.darktv.in/c", "params": { "mac": "00:1A:79:32:A5:94" } },
  { "name": "DarkTV 8", "type": "stalker", "url": "http://iptv.darktv.in/c", "params": { "mac": "00:1A:79:BF:DE:E4" } },
  { "name": "DarkTV 9", "type": "stalker", "url": "http://iptv.darktv.in/c", "params": { "mac": "00:1A:79:19:07:72" } },
  { "name": "DarkTV 10", "type": "stalker", "url": "http://iptv.darktv.in/c", "params": { "mac": "00:1A:79:C3:9F:0E" } },
  { "name": "KingTV 1", "type": "stalker", "url": "http://ix.kingtv.pw/c", "params": { "mac": "00:1A:79:D2:B9:B8" } },
  { "name": "KingTV 2", "type": "stalker", "url": "http://ix.kingtv.pw/c", "params": { "mac": "00:1A:79:6B:BE:B9" } },
  { "name": "KingTV 3", "type": "stalker", "url": "http://ix.kingtv.pw/c", "params": { "mac": "00:1A:79:0F:46:C4" } },
  { "name": "KingTV 4", "type": "stalker", "url": "http://ix.kingtv.pw/c", "params": { "mac": "00:1A:79:9E:86:C3" } },
  { "name": "KingTV 5", "type": "stalker", "url": "http://ix.kingtv.pw/c", "params": { "mac": "00:1A:79:07:BE:90" } },
  { "name": "KingTV 6", "type": "stalker", "url": "http://ix.kingtv.pw/c", "params": { "mac": "00:1A:79:44:B3:F4" } },
  { "name": "KingTV 7", "type": "stalker", "url": "http://ix.kingtv.pw/c", "params": { "mac": "00:1A:79:6B:BE:BD" } },
  { "name": "KingTV 8", "type": "stalker", "url": "http://ix.kingtv.pw/c", "params": { "mac": "00:1A:79:9D:F0:7E" } },
  { "name": "KingTV 9", "type": "stalker", "url": "http://ix.kingtv.pw/c", "params": { "mac": "00:1A:79:9E:88:81" } },
  { "name": "KingTV 10", "type": "stalker", "url": "http://ix.kingtv.pw/c", "params": { "mac": "00:1A:79:A5:C1:11" } },
  { "name": "StreamTV Auth 1", "type": "stalker", "url": "http://auth.streamtv.to:8080/c", "params": { "mac": "00:1A:79:2B:A2:E3" } },
  { "name": "StreamTV Auth 2", "type": "stalker", "url": "http://auth.streamtv.to:8080/c", "params": { "mac": "00:1A:79:5F:DD:0B" } },
  { "name": "StreamTV Auth 3", "type": "stalker", "url": "http://auth.streamtv.to:8080/c", "params": { "mac": "00:1A:79:B5:2C:6A" } },
  { "name": "StreamTV Auth 4", "type": "stalker", "url": "http://auth.streamtv.to:8080/c", "params": { "mac": "00:1A:79:2B:7C:24" } },
  { "name": "StreamTV Auth 5", "type": "stalker", "url": "http://auth.streamtv.to:8080/c", "params": { "mac": "00:1A:79:C8:33:8C" } },
  { "name": "StreamTV Dana", "type": "stalker", "url": "http://danatv.tv.streamtv.to:8080/c", "params": { "mac": "00:1A:79:AA:66:8D" } },
  { "name": "StreamTV Owl", "type": "stalker", "url": "http://owliptv.streamtv.to:8080/c", "params": { "mac": "00:1A:79:FE:5A:81" } },
  { "name": "Banjotv 1", "type": "stalker", "url": "http://tv.banjotv.tv/stalker_portal/c", "params": { "mac": "00:1A:79:0F:CA:51" } },
  { "name": "Banjotv 2", "type": "stalker", "url": "http://tv.banjotv.tv/stalker_portal/c", "params": { "mac": "00:1A:79:A4:99:A9" } },
  { "name": "IPTV Rocket 1", "type": "stalker", "url": "http://p1.iptvrocket.tv/c", "params": { "mac": "00:1A:79:BD:4F:BA" } },
  { "name": "IPTV Rocket 2", "type": "stalker", "url": "http://p1.iptvrocket.tv/c", "params": { "mac": "00:1A:79:5B:BE:27" } },
  { "name": "Frt23", "type": "stalker", "url": "http://frt23.mi20.cc/stalker_portal/c", "params": { "mac": "00:1A:79:D3:4D:98" } },
  { "name": "CWDN", "type": "stalker", "url": "http://main2.cwdn.cx/c", "params": { "mac": "00:1A:79:C3:10:51" } },
  { "name": "SecretService", "type": "stalker", "url": "http://secretservice.cc/c", "params": { "mac": "00:1A:79:37:C9:89" } },
  { "name": "TvSet", "type": "stalker", "url": "http://xc.tvset.top/c", "params": { "mac": "00:1A:79:0E:85:CA" } }
]
